CONTRIBUTING.md
MANIFEST.in
README.rst
setup.py
docs/HISTORY.txt
docs/LICENSE.GPL
docs/LICENSE.txt
eea/__init__.py
eea.dexterity.indicators.egg-info/PKG-INFO
eea.dexterity.indicators.egg-info/SOURCES.txt
eea.dexterity.indicators.egg-info/dependency_links.txt
eea.dexterity.indicators.egg-info/entry_points.txt
eea.dexterity.indicators.egg-info/namespace_packages.txt
eea.dexterity.indicators.egg-info/not-zip-safe
eea.dexterity.indicators.egg-info/requires.txt
eea.dexterity.indicators.egg-info/top_level.txt
eea/dexterity/__init__.py
eea/dexterity/indicators/README.txt
eea/dexterity/indicators/__init__.py
eea/dexterity/indicators/configure.zcml
eea/dexterity/indicators/indexer.py
eea/dexterity/indicators/interfaces.py
eea/dexterity/indicators/permissions.zcml
eea/dexterity/indicators/profiles.zcml
eea/dexterity/indicators/setuphandlers.py
eea/dexterity/indicators/version.txt
eea/dexterity/indicators/behaviors/__init__.py
eea/dexterity/indicators/behaviors/configure.zcml
eea/dexterity/indicators/behaviors/indicator.py
eea/dexterity/indicators/browser/__init__.py
eea/dexterity/indicators/browser/configure.zcml
eea/dexterity/indicators/contentrules/__init__.py
eea/dexterity/indicators/contentrules/actions.py
eea/dexterity/indicators/contentrules/configure.zcml
eea/dexterity/indicators/contentrules/version.py
eea/dexterity/indicators/locales/__init__.py
eea/dexterity/indicators/locales/eea.pot
eea/dexterity/indicators/locales/plone-manual.pot
eea/dexterity/indicators/locales/update.sh
eea/dexterity/indicators/locales/bg/LC_MESSAGES/eea.mo
eea/dexterity/indicators/locales/bg/LC_MESSAGES/eea.po
eea/dexterity/indicators/locales/bg/LC_MESSAGES/plone.mo
eea/dexterity/indicators/locales/bg/LC_MESSAGES/plone.po
eea/dexterity/indicators/locales/cs/LC_MESSAGES/eea.mo
eea/dexterity/indicators/locales/cs/LC_MESSAGES/eea.po
eea/dexterity/indicators/locales/cs/LC_MESSAGES/plone.mo
eea/dexterity/indicators/locales/cs/LC_MESSAGES/plone.po
eea/dexterity/indicators/locales/da/LC_MESSAGES/eea.mo
eea/dexterity/indicators/locales/da/LC_MESSAGES/eea.po
eea/dexterity/indicators/locales/da/LC_MESSAGES/plone.mo
eea/dexterity/indicators/locales/da/LC_MESSAGES/plone.po
eea/dexterity/indicators/locales/de/LC_MESSAGES/eea.mo
eea/dexterity/indicators/locales/de/LC_MESSAGES/eea.po
eea/dexterity/indicators/locales/de/LC_MESSAGES/plone.mo
